LICENSE
MANIFEST.in
README.rst
setup.py
banzai/__init__.py
banzai/admin.py
banzai/api.py
banzai/base.py
banzai/mail.py
banzai/models.py
banzai/settings.py
banzai/migrations/0001_initial.py
banzai/migrations/0002_auto__add_field_package_created_on.py
banzai/migrations/__init__.py
django_banzai.egg-info/PKG-INFO
django_banzai.egg-info/SOURCES.txt
django_banzai.egg-info/dependency_links.txt
django_banzai.egg-info/requires.txt
django_banzai.egg-info/top_level.txt
test_project/__init__.py
test_project/manage.py
test_project/settings.py
test_project/urls.py