Metadata-Version: 1.1
Name: django-banzai
Version: 0.2
Summary: Django API wrapper for mailing delivery service: http://get-n-post.ru/
Home-page: https://github.com/saippuakauppias/django-banzai
Author: Denis Veselov
Author-email: progr.mail@gmail.com
License: MIT
Keywords: mail email send wrapper api delivery django
Platform: UNKNOWN
Classifier: Development Status :: 4 - Beta
Classifier: Intended Audience :: Developers
Classifier: Operating System :: OS Independent
Classifier: Programming Language :: Python
Classifier: Programming Language :: Python :: 2.6
Classifier: Programming Language :: Python :: 2.7
Classifier: Topic :: Internet :: WWW/HTTP
